{
    "dashoard_label":"Dashboard",
    "default_label":"Default",
    "ecommerce_label":"E Commerce",
    "crm_label":"CRM",
    "orders_label":"Orders",
    "search_label":"Search",
    "sno_lable":"S.No",
    "order_no_label":"Order Number",
    "customer_no_label":"Customer Number",
    "po_no_label":"P.O Number",
    "shipping_date_label":"Shipping date",
    "shipping_method_label":"Shipping Method",
    "part_number_label":"Part Number",
    "quantity_label":"Quantity",
    "comments_label":"Comments",
    "status_label":"Status",
    "receiving_label": "Receiving",
    "production_label": "Production",
    "Orders_label": "Orders",
    "warehouse_label":"Warehouse",
    "outgoing_label":"Outgoing",
    "sales_label":"Sales Orders",
    "accounts_label":"A/R",
    "charts_label":"Charts",
    "applications_label":"Applications",
    "analytics_label":"Analytics",
    "projects_label":"Projects",
    "tables_label":"Data Tables",
    "reports_label":"Reports",
    "authentication_label": "Authentication",
    "signin_label":"Sign in",
    "signup_label":"Sign up",
    "reset_label":"Reset",
    "verification_label": "2-Step Verification"
   


}